pomegranate/__init__.py
pomegranate/_bayes.py
pomegranate/_utils.py
pomegranate/bayes_classifier.py
pomegranate/bayesian_network.py
pomegranate/factor_graph.py
pomegranate/gmm.py
pomegranate/kmeans.py
pomegranate/markov_chain.py
pomegranate/distributions/__init__.py
pomegranate/distributions/_distribution.py
pomegranate/distributions/bernoulli.py
pomegranate/distributions/categorical.py
pomegranate/distributions/conditional_categorical.py
pomegranate/distributions/dirac_delta.py
pomegranate/distributions/exponential.py
pomegranate/distributions/gamma.py
pomegranate/distributions/halfnormal.py
pomegranate/distributions/independent_components.py
pomegranate/distributions/joint_categorical.py
pomegranate/distributions/lognormal.py
pomegranate/distributions/normal.py
pomegranate/distributions/poisson.py
pomegranate/distributions/student_t.py
pomegranate/distributions/uniform.py
pomegranate/distributions/zero_inflated.py
pomegranate/hmm/__init__.py
pomegranate/hmm/_base.py
pomegranate/hmm/dense_hmm.py
pomegranate/hmm/sparse_hmm.py
pomegranate-1.1.2.dist-info/LICENSE
pomegranate-1.1.2.dist-info/METADATA
pomegranate-1.1.2.dist-info/WHEEL
pomegranate-1.1.2.dist-info/top_level.txt
pomegranate-1.1.2.dist-info/RECORD
